daprgen/.DS_Store
daprgen/__init__.py
daprgen/api.py
daprgen/cli.py
daprgen/domain/__init__.py
daprgen/domain/ghl_oauth_schema.py
daprgen/domain/ghl_oauth_service.py
daprgen/domain/oauth_models.py
daprgen/domain/oauth_service.py
daprgen/experiments/__init__.py
daprgen/experiments/ghl_schema/__init__.py
daprgen/experiments/ghl_schema/calendar_schema_parser.py
daprgen/experiments/ghl_schema/calendar_test.py
daprgen/experiments/ghl_schema/calendars.json
daprgen/experiments/ghl_schema/oauth.json
daprgen/experiments/ghl_schema/oauth_schema_parser.py
daprgen/experiments/ghl_schema/output/ghl_oauth_models.py
daprgen/experiments/ghl_schema/output/ghl_oauth_service.py
daprgen/ghl.py
daprgen/infrastructure/__init__.py
daprgen/infrastructure/config.py
daprgen/installationObjects.json
daprgen/mixins/__init__.py
daprgen/mixins/ghl_service_mixin.py
daprgen/mocks.py
daprgen/model.py
daprgen/prototypes/__init__.py
daprgen/prototypes/calendar/__init__.py
daprgen/prototypes/calendar/app_di_config.py
daprgen/prototypes/calendar/appointment.py
daprgen/prototypes/calendar/events.py
daprgen/prototypes/calendar/ghl_calendar_models.py
daprgen/prototypes/calendar/ghl_calendar_service.py
daprgen/prototypes/calendar/models.py
daprgen/prototypes/calendar/repository.py
daprgen/prototypes/calendar/service.py
daprgen/prototypes/create_resource.py
daprgen/routes/__init__.py
daprgen/routes/ghl_routes.py
daprgen/routes/oauth_routes.py
daprgen/utils/__init__.py
daprgen/utils/httpx_tools.py
daprgen-2024.5.24.dist-info/LICENSE
daprgen-2024.5.24.dist-info/METADATA
daprgen-2024.5.24.dist-info/WHEEL
daprgen-2024.5.24.dist-info/entry_points.txt
daprgen-2024.5.24.dist-info/RECORD
