Metadata-Version: 2.1
Name: daprgen
Version: 2024.5.24
Summary: TODO
Home-page: https://github.com/to/do
Author: Sean Chatman
Author-email: info@chatmangpt.com
Requires-Python: >=3.10,<3.12
Classifier: Programming Language :: Python :: 3
Classifier: Programming Language :: Python :: 3.10
Classifier: Programming Language :: Python :: 3.11
Requires-Dist: aiohttp[speedups] (>=3.9.5,<4.0.0)
Requires-Dist: coloredlogs (>=15.0.1)
Requires-Dist: dspygen (>=2024.5.16,<2025.0.0)
Requires-Dist: factory-boy (>=3.3.0,<4.0.0)
Requires-Dist: fastapi[all] (>=0.110.1)
Requires-Dist: gunicorn (>=21.2.0)
Requires-Dist: httpx (>=0.27.0,<0.28.0)
Requires-Dist: inject (>=5.2.1,<6.0.0)
Requires-Dist: poethepoet (>=0.25.0)
Requires-Dist: pycryptodome (>=3.20.0,<4.0.0)
Requires-Dist: pyngrok (>=7.1.6,<8.0.0)
Requires-Dist: pytest-bdd (>=7.1.2,<8.0.0)
Requires-Dist: pytest-httpx (>=0.30.0,<0.31.0)
Requires-Dist: pytest-mock (>=3.14.0,<4.0.0)
Requires-Dist: pytest-vcr (>=1.0.2,<2.0.0)
Requires-Dist: typer[all] (>=0.12.0)
Requires-Dist: uvicorn[standard] (>=0.29.0)
Project-URL: Repository, https://github.com/to/do
